lib/__init__.py
lib/cdlab.py
upecd-0.0.1.dist-info/METADATA
upecd-0.0.1.dist-info/WHEEL
upecd-0.0.1.dist-info/top_level.txt
upecd-0.0.1.dist-info/RECORD
