Metadata-Version: 2.1
Name: upecd
Version: 0.0.1
Summary: practical exam
Author: AK
Author-email: <arkenkumar@gmail.com>
Keywords: python,video,stream,video stream,camera stream,sockets
